pyscreamor/__init__.py
pyscreamor/pyscreamor.service
pyscreamor/screamor.py
pyscreamor-0.0.3.dist-info/METADATA
pyscreamor-0.0.3.dist-info/WHEEL
pyscreamor-0.0.3.dist-info/top_level.txt
pyscreamor-0.0.3.dist-info/RECORD
